CHANGELOG.rst
LICENSE
MANIFEST.in
README.md
README.rst
requirements.txt
run.py
setup.py
docs/Makefile
docs/api.rst
docs/changelog.rst
docs/cli.rst
docs/conf.py
docs/gui.rst
docs/index.rst
docs/license.rst
docs/make.bat
docs/requirements-rtd.txt
docs/_build/html/_images/home.png
docs/_build/html/_images/molfile_base.png
docs/_build/html/_images/molfile_repr.png
docs/_build/html/_images/nmrtable.png
docs/_build/html/_images/nmrtable_save.png
docs/_build/html/_images/nmrtable_select.png
docs/_build/html/_images/nmrtable_select_sort.png
docs/_build/html/_images/table.png
docs/_build/html/_images/table_add_row.png
docs/_build/html/_images/table_add_row_update.png
docs/_build/html/_images/table_generate_nmr_inchi.png
docs/_build/html/_images/table_iso.png
docs/_build/html/_images/table_iso_chg.png
docs/_build/html/_images/table_remove_row.png
docs/_build/html/_images/table_save.png
docs/_build/html/_sources/api.rst.txt
docs/_build/html/_sources/changelog.rst.txt
docs/_build/html/_sources/cli.rst.txt
docs/_build/html/_sources/gui.rst.txt
docs/_build/html/_sources/index.rst.txt
docs/_build/html/_sources/license.rst.txt
docs/_build/html/_static/file.png
docs/_build/html/_static/minus.png
docs/_build/html/_static/plus.png
docs/_build/html/_static/fonts/fontawesome-webfont.svg
docs/_build/html/_static/gui/home.png
docs/_build/html/_static/gui/molfile_base.png
docs/_build/html/_static/gui/molfile_repr.png
docs/_build/html/_static/gui/nmrtable.png
docs/_build/html/_static/gui/nmrtable_save.png
docs/_build/html/_static/gui/nmrtable_select.png
docs/_build/html/_static/gui/nmrtable_select_sort.png
docs/_build/html/_static/gui/table.png
docs/_build/html/_static/gui/table_add_row.png
docs/_build/html/_static/gui/table_add_row_update.png
docs/_build/html/_static/gui/table_generate_nmr_inchi.png
docs/_build/html/_static/gui/table_iso.png
docs/_build/html/_static/gui/table_iso_chg.png
docs/_build/html/_static/gui/table_remove_row.png
docs/_build/html/_static/gui/table_save.png
isoenum_webgui.egg-info/PKG-INFO
isoenum_webgui.egg-info/SOURCES.txt
isoenum_webgui.egg-info/dependency_links.txt
isoenum_webgui.egg-info/entry_points.txt
isoenum_webgui.egg-info/requires.txt
isoenum_webgui.egg-info/top_level.txt
